{
	"cmake" : 
	{
		"generator" : 
		{
			"multiConfig" : false,
			"name" : "Ninja"
		},
		"paths" : 
		{
			"cmake" : "E:/Programs/JetBrains/CLion/bin/cmake/win/x64/bin/cmake.exe",
			"cpack" : "E:/Programs/JetBrains/CLion/bin/cmake/win/x64/bin/cpack.exe",
			"ctest" : "E:/Programs/JetBrains/CLion/bin/cmake/win/x64/bin/ctest.exe",
			"root" : "E:/Programs/JetBrains/CLion/bin/cmake/win/x64/share/cmake-3.30"
		},
		"version" : 
		{
			"isDirty" : false,
			"major" : 3,
			"minor" : 30,
			"patch" : 5,
			"string" : "3.30.5",
			"suffix" : ""
		}
	},
	"objects" : 
	[
		{
			"jsonFile" : "codemodel-v2-35f3ffe7d20a15708b3e.json",
			"kind" : "codemodel",
			"version" : 
			{
				"major" : 2,
				"minor" : 7
			}
		},
		{
			"jsonFile" : "cache-v2-cca253b325d7145c2207.json",
			"kind" : "cache",
			"version" : 
			{
				"major" : 2,
				"minor" : 0
			}
		},
		{
			"jsonFile" : "cmakeFiles-v1-ceed6e601d6ea08b428e.json",
			"kind" : "cmakeFiles",
			"version" : 
			{
				"major" : 1,
				"minor" : 1
			}
		},
		{
			"jsonFile" : "toolchains-v1-383b04051d8ff6e85417.json",
			"kind" : "toolchains",
			"version" : 
			{
				"major" : 1,
				"minor" : 0
			}
		}
	],
	"reply" : 
	{
		"cache-v2" : 
		{
			"jsonFile" : "cache-v2-cca253b325d7145c2207.json",
			"kind" : "cache",
			"version" : 
			{
				"major" : 2,
				"minor" : 0
			}
		},
		"cmakeFiles-v1" : 
		{
			"jsonFile" : "cmakeFiles-v1-ceed6e601d6ea08b428e.json",
			"kind" : "cmakeFiles",
			"version" : 
			{
				"major" : 1,
				"minor" : 1
			}
		},
		"codemodel-v2" : 
		{
			"jsonFile" : "codemodel-v2-35f3ffe7d20a15708b3e.json",
			"kind" : "codemodel",
			"version" : 
			{
				"major" : 2,
				"minor" : 7
			}
		},
		"toolchains-v1" : 
		{
			"jsonFile" : "toolchains-v1-383b04051d8ff6e85417.json",
			"kind" : "toolchains",
			"version" : 
			{
				"major" : 1,
				"minor" : 0
			}
		}
	}
}
